test.py
arctic_orchestra/__init__.py
arctic_orchestra/Agents/    __init__.py
arctic_orchestra/Agents/base.py
arctic_orchestra/Agents/loop_agent.py
arctic_orchestra/Agents/router_agent.py
arctic_orchestra/Agents/sequential_agent.py
arctic_orchestra/Agents/simple_agent.py
arctic_orchestra/Models/__init__.py
arctic_orchestra/Models/google_gemini.py
arctic_orchestra/Models/openrouter_qwen.py
arctic_orchestra/Tools/__init__.py
arctic_orchestra/Tools/agent_2_tool.py
arctic_orchestra-0.1.3.dist-info/licenses/LICENSE
arctic_orchestra-0.1.3.dist-info/METADATA
arctic_orchestra-0.1.3.dist-info/WHEEL
arctic_orchestra-0.1.3.dist-info/top_level.txt
arctic_orchestra-0.1.3.dist-info/RECORD
