Metadata-Version: 2.4
Name: arctic-orchestra
Version: 0.1.3
Summary: Arctic-Orchestra: A modular agent orchestration framework
Author: Abhigyan
License:                                  Apache License
Project-URL: Homepage, https://github.com/Abhigyan126/Arctic-Orchestra
Project-URL: Source, https://github.com/Abhigyan126/Arctic-Orchestra
Project-URL: Issues, https://github.com/Abhigyan126/Arctic-Orchestra/issues
Requires-Python: >=3.9
License-File: LICENSE
Requires-Dist: python-dotenv==1.2.1
Requires-Dist: requests==2.32.5
Requires-Dist: google-genai==1.52.0
Requires-Dist: google-auth==2.43.0
Dynamic: license-file
